rail/delight/__init__.py
rail/delight/_version.py
rail/estimation/algos/delight_hybrid.py
rail/examples_data/estimation_data/data/FILTER/DC2LSST_g.res
rail/examples_data/estimation_data/data/FILTER/DC2LSST_g_gaussian_coefficients.txt
rail/examples_data/estimation_data/data/FILTER/DC2LSST_i.res
rail/examples_data/estimation_data/data/FILTER/DC2LSST_i_gaussian_coefficients.txt
rail/examples_data/estimation_data/data/FILTER/DC2LSST_r.res
rail/examples_data/estimation_data/data/FILTER/DC2LSST_r_gaussian_coefficients.txt
rail/examples_data/estimation_data/data/FILTER/DC2LSST_u.res
rail/examples_data/estimation_data/data/FILTER/DC2LSST_u_gaussian_coefficients.txt
rail/examples_data/estimation_data/data/FILTER/DC2LSST_y.res
rail/examples_data/estimation_data/data/FILTER/DC2LSST_y_gaussian_coefficients.txt
rail/examples_data/estimation_data/data/FILTER/DC2LSST_z.res
rail/examples_data/estimation_data/data/FILTER/DC2LSST_z_gaussian_coefficients.txt
rail/examples_data/estimation_data/data/SED/CWWSB4.list
rail/examples_data/estimation_data/data/SED/El_B2004a.sed
rail/examples_data/estimation_data/data/SED/El_B2004a_fluxredshiftmod.txt
rail/examples_data/estimation_data/data/SED/Im_B2004a.sed
rail/examples_data/estimation_data/data/SED/Im_B2004a_fluxredshiftmod.txt
rail/examples_data/estimation_data/data/SED/SB2_B2004a.sed
rail/examples_data/estimation_data/data/SED/SB2_B2004a_fluxredshiftmod.txt
rail/examples_data/estimation_data/data/SED/SB3_B2004a.sed
rail/examples_data/estimation_data/data/SED/SB3_B2004a_fluxredshiftmod.txt
rail/examples_data/estimation_data/data/SED/Sbc_B2004a.sed
rail/examples_data/estimation_data/data/SED/Sbc_B2004a_fluxredshiftmod.txt
rail/examples_data/estimation_data/data/SED/Scd_B2004a.sed
rail/examples_data/estimation_data/data/SED/Scd_B2004a_fluxredshiftmod.txt
rail/examples_data/estimation_data/data/SED/ssp_25Myr_z008.sed
rail/examples_data/estimation_data/data/SED/ssp_25Myr_z008_fluxredshiftmod.txt
pz_rail_delight-1.0.1.dist-info/LICENSE
pz_rail_delight-1.0.1.dist-info/METADATA
pz_rail_delight-1.0.1.dist-info/WHEEL
pz_rail_delight-1.0.1.dist-info/top_level.txt
pz_rail_delight-1.0.1.dist-info/RECORD
